{
  "name": "Pradeep Jaikumar",
  "title": "Founder & Managing Director",
  "experience": "16+ Years of Experience",
  "address": "52A, 120 feet Surveyor Colony Road, Mattuthavani, Madurai",
  "phone": "+91 82303 00000",
  "email": "info@bhimahomes.in",
  "bio": "Pradeep Jaikumar founded Bhima Homes and Properties in 2010 with a vision to bring professional-grade property consulting to Madurai. Leading a team of architects, civil engineers, and legal experts, he has built the company into a trusted name in the region. From technical verification to legal opinions and registration, Bhima Homes offers end-to-end property services.",
  "image": ""
}